{"id":"/subscriptions/bbd83110-10a9-4d2f-9b08-ec69f129c56b/resourceGroups/webflowersproductcentral/providers/Microsoft.ClassicCompute/domainNames/webflowersproductcentral/slots/Production/roles/GloboStudio.Core.WebServices/metrics","value":[{"name":{"value":"Percentage CPU","localizedValue":"CPU Percentage"},"unit":"Percent","timeGrain":"PT1H","startTime":"2019-10-01T15:00:00Z","endTime":"2019-10-08T07:00:00Z","metricValues":[{"timestamp":"2019-10-01T15:00:00Z","average":1.5788655462184873,"minimum":0.94,"maximum":6.19,"total":375.77,"count":238,"properties":[]},{"timestamp":"2019-10-01T16:00:00Z","average":1.5136401673640167,"minimum":0.98,"maximum":5.15,"total":361.76,"count":239,"properties":[]},{"timestamp":"2019-10-01T17:00:00Z","average":1.55718487394958,"minimum":0.99,"maximum":6.81,"total":370.61,"count":238,"properties":[]},{"timestamp":"2019-10-01T18:00:00Z","average":1.7266386554621849,"minimum":0.97,"maximum":6.79,"total":410.94,"count":238,"properties":[]},{"timestamp":"2019-10-01T19:00:00Z","average":1.7273529411764705,"minimum":1.05,"maximum":6.73,"total":411.11,"count":238,"properties":[]},{"timestamp":"2019-10-01T20:00:00Z","average":1.6852301255230124,"minimum":1.06,"maximum":6.75,"total":402.77,"count":239,"properties":[]},{"timestamp":"2019-10-01T21:00:00Z","average":1.8739915966386553,"minimum":1.06,"maximum":22.94,"total":446.01,"count":238,"properties":[]},{"timestamp":"2019-10-01T22:00:00Z","average":1.6377731092436973,"minimum":1.05,"maximum":5.82,"total":389.78999999999996,"count":238,"properties":[]},{"timestamp":"2019-10-01T23:00:00Z","average":1.643109243697479,"minimum":1.04,"maximum":5.18,"total":391.06,"count":238,"properties":[]},{"timestamp":"2019-10-02T00:00:00Z","average":1.6885294117647058,"minimum":1.04,"maximum":6.99,"total":401.87,"count":238,"properties":[]},{"timestamp":"2019-10-02T01:00:00Z","average":1.5400840336134451,"minimum":1.02,"maximum":6.79,"total":366.53999999999996,"count":238,"properties":[]},{"timestamp":"2019-10-02T02:00:00Z","average":1.5881932773109244,"minimum":1.02,"maximum":5.55,"total":377.99,"count":238,"properties":[]},{"timestamp":"2019-10-02T03:00:00Z","average":1.576652719665272,"minimum":0.97,"maximum":6.37,"total":376.82,"count":239,"properties":[]},{"timestamp":"2019-10-02T04:00:00Z","average":1.5344537815126051,"minimum":1.02,"maximum":6.55,"total":365.20000000000005,"count":238,"properties":[]},{"timestamp":"2019-10-02T05:00:00Z","average":1.64327731092437,"minimum":1.02,"maximum":10.55,"total":391.1,"count":238,"properties":[]},{"timestamp":"2019-10-02T06:00:00Z","average":1.6592857142857143,"minimum":0.95,"maximum":10.21,"total":394.90999999999997,"count":238,"properties":[]},{"timestamp":"2019-10-02T07:00:00Z","average":1.6476569037656903,"minimum":0.97,"maximum":5.52,"total":393.78999999999996,"count":239,"properties":[]},{"timestamp":"2019-10-02T08:00:00Z","average":1.7140756302521007,"minimum":1.04,"maximum":7.29,"total":407.95,"count":238,"properties":[]},{"timestamp":"2019-10-02T09:00:00Z","average":1.6931932773109244,"minimum":0.99,"maximum":6.94,"total":402.98,"count":238,"properties":[]},{"timestamp":"2019-10-02T10:00:00Z","average":1.6191596638655463,"minimum":0.99,"maximum":6.75,"total":385.36,"count":238,"properties":[]},{"timestamp":"2019-10-02T11:00:00Z","average":1.6111764705882354,"minimum":0.99,"maximum":7.06,"total":383.46000000000004,"count":238,"properties":[]},{"timestamp":"2019-10-02T12:00:00Z","average":1.9993277310924371,"minimum":0.99,"maximum":15.82,"total":475.84000000000003,"count":238,"properties":[]},{"timestamp":"2019-10-02T13:00:00Z","average":1.7812133891213391,"minimum":1.03,"maximum":19.75,"total":425.71000000000004,"count":239,"properties":[]},{"timestamp":"2019-10-02T14:00:00Z","average":1.56890756302521,"minimum":1.01,"maximum":7.47,"total":373.4,"count":238,"properties":[]},{"timestamp":"2019-10-02T15:00:00Z","average":1.5512184873949579,"minimum":1.01,"maximum":5.51,"total":369.19,"count":238,"properties":[]},{"timestamp":"2019-10-02T16:00:00Z","average":1.6077731092436973,"minimum":1.02,"maximum":8.83,"total":382.65,"count":238,"properties":[]},{"timestamp":"2019-10-02T17:00:00Z","average":1.7136554621848741,"minimum":1.05,"maximum":5.98,"total":407.85,"count":238,"properties":[]},{"timestamp":"2019-10-02T18:00:00Z","average":1.7054811715481173,"minimum":1.06,"maximum":7.31,"total":407.61,"count":239,"properties":[]},{"timestamp":"2019-10-02T19:00:00Z","average":1.7284453781512605,"minimum":1.04,"maximum":7.32,"total":411.37,"count":238,"properties":[]},{"timestamp":"2019-10-02T20:00:00Z","average":1.6693277310924368,"minimum":1.06,"maximum":6.01,"total":397.29999999999995,"count":238,"properties":[]},{"timestamp":"2019-10-02T21:00:00Z","average":1.6902100840336134,"minimum":1.03,"maximum":6.3,"total":402.27,"count":238,"properties":[]},{"timestamp":"2019-10-02T22:00:00Z","average":1.7229411764705882,"minimum":0.99,"maximum":7.19,"total":410.06,"count":238,"properties":[]},{"timestamp":"2019-10-02T23:00:00Z","average":1.7731932773109242,"minimum":1.01,"maximum":6.57,"total":422.02,"count":238,"properties":[]},{"timestamp":"2019-10-03T00:00:00Z","average":1.618235294117647,"minimum":1.0,"maximum":6.78,"total":385.14,"count":238,"properties":[]},{"timestamp":"2019-10-03T01:00:00Z","average":1.5946218487394956,"minimum":1.03,"maximum":6.59,"total":379.52,"count":238,"properties":[]},{"timestamp":"2019-10-03T02:00:00Z","average":1.6497058823529411,"minimum":1.07,"maximum":7.13,"total":392.63,"count":238,"properties":[]},{"timestamp":"2019-10-03T03:00:00Z","average":1.6631512605042016,"minimum":0.98,"maximum":5.95,"total":395.83,"count":238,"properties":[]},{"timestamp":"2019-10-03T04:00:00Z","average":1.6645378151260504,"minimum":1.06,"maximum":5.46,"total":396.15999999999997,"count":238,"properties":[]},{"timestamp":"2019-10-03T05:00:00Z","average":1.7060251046025106,"minimum":1.1,"maximum":7.35,"total":407.74,"count":239,"properties":[]},{"timestamp":"2019-10-03T06:00:00Z","average":1.5987394957983194,"minimum":1.06,"maximum":6.47,"total":380.5,"count":238,"properties":[]},{"timestamp":"2019-10-03T07:00:00Z","average":1.7522268907563023,"minimum":1.1,"maximum":9.84,"total":417.03,"count":238,"properties":[]},{"timestamp":"2019-10-03T08:00:00Z","average":1.701255230125523,"minimum":1.08,"maximum":6.73,"total":406.6,"count":239,"properties":[]},{"timestamp":"2019-10-03T09:00:00Z","average":1.6291176470588236,"minimum":1.05,"maximum":5.7,"total":387.73,"count":238,"properties":[]},{"timestamp":"2019-10-03T10:00:00Z","average":1.55890756302521,"minimum":1.07,"maximum":7.02,"total":371.02,"count":238,"properties":[]},{"timestamp":"2019-10-03T11:00:00Z","average":1.6119747899159662,"minimum":1.06,"maximum":6.63,"total":383.65,"count":238,"properties":[]},{"timestamp":"2019-10-03T12:00:00Z","average":1.5756302521008403,"minimum":1.07,"maximum":6.91,"total":375.0,"count":238,"properties":[]},{"timestamp":"2019-10-03T13:00:00Z","average":1.5594957983193276,"minimum":1.05,"maximum":5.15,"total":371.15999999999997,"count":238,"properties":[]},{"timestamp":"2019-10-03T14:00:00Z","average":1.7583193277310925,"minimum":1.11,"maximum":7.15,"total":418.48,"count":238,"properties":[]},{"timestamp":"2019-10-03T15:00:00Z","average":1.6828991596638654,"minimum":1.08,"maximum":5.85,"total":400.53,"count":238,"properties":[]},{"timestamp":"2019-10-03T16:00:00Z","average":1.6677731092436974,"minimum":1.05,"maximum":5.5,"total":396.92999999999995,"count":238,"properties":[]},{"timestamp":"2019-10-03T17:00:00Z","average":1.7907949790794979,"minimum":1.07,"maximum":6.88,"total":428.0,"count":239,"properties":[]},{"timestamp":"2019-10-03T18:00:00Z","average":1.7447899159663864,"minimum":1.07,"maximum":6.82,"total":415.26,"count":238,"properties":[]},{"timestamp":"2019-10-03T19:00:00Z","average":1.6071428571428572,"minimum":1.05,"maximum":7.35,"total":382.5,"count":238,"properties":[]},{"timestamp":"2019-10-03T20:00:00Z","average":1.6168396226415094,"minimum":1.05,"maximum":6.05,"total":342.77,"count":212,"properties":[]},{"timestamp":"2019-10-03T21:00:00Z","average":1.4938853503184715,"minimum":0.9,"maximum":5.9,"total":234.54000000000002,"count":157,"properties":[]},{"timestamp":"2019-10-03T22:00:00Z","average":2.2065966386554625,"minimum":0.85,"maximum":52.61,"total":525.17000000000007,"count":238,"properties":[]},{"timestamp":"2019-10-03T23:00:00Z","average":1.5794537815126048,"minimum":0.89,"maximum":6.35,"total":375.90999999999997,"count":238,"properties":[]},{"timestamp":"2019-10-04T00:00:00Z","average":1.5842016806722687,"minimum":0.87,"maximum":7.09,"total":377.03999999999996,"count":238,"properties":[]},{"timestamp":"2019-10-04T01:00:00Z","average":1.6145798319327731,"minimum":0.92,"maximum":6.59,"total":384.27,"count":238,"properties":[]},{"timestamp":"2019-10-04T02:00:00Z","average":1.6361764705882351,"minimum":0.92,"maximum":6.88,"total":389.40999999999997,"count":238,"properties":[]},{"timestamp":"2019-10-04T03:00:00Z","average":1.7251046025104602,"minimum":0.91,"maximum":7.38,"total":412.29999999999995,"count":239,"properties":[]},{"timestamp":"2019-10-04T04:00:00Z","average":1.6426470588235293,"minimum":0.9,"maximum":7.61,"total":390.95,"count":238,"properties":[]},{"timestamp":"2019-10-04T05:00:00Z","average":1.6183613445378151,"minimum":0.88,"maximum":6.38,"total":385.17,"count":238,"properties":[]},{"timestamp":"2019-10-04T06:00:00Z","average":1.6068487394957984,"minimum":0.91,"maximum":5.02,"total":382.43,"count":238,"properties":[]},{"timestamp":"2019-10-04T07:00:00Z","average":1.6415899581589959,"minimum":0.91,"maximum":10.08,"total":392.34000000000003,"count":239,"properties":[]},{"timestamp":"2019-10-04T08:00:00Z","average":1.6707142857142856,"minimum":0.87,"maximum":20.51,"total":397.63,"count":238,"properties":[]},{"timestamp":"2019-10-04T09:00:00Z","average":1.7100000000000002,"minimum":0.89,"maximum":21.77,"total":406.98,"count":238,"properties":[]},{"timestamp":"2019-10-04T10:00:00Z","average":1.6645378151260504,"minimum":0.91,"maximum":7.18,"total":396.15999999999997,"count":238,"properties":[]},{"timestamp":"2019-10-04T11:00:00Z","average":1.6205882352941177,"minimum":0.89,"maximum":7.49,"total":385.7,"count":238,"properties":[]},{"timestamp":"2019-10-04T12:00:00Z","average":1.5530543933054393,"minimum":0.93,"maximum":5.26,"total":371.18,"count":239,"properties":[]},{"timestamp":"2019-10-04T13:00:00Z","average":1.6581092436974789,"minimum":0.92,"maximum":7.04,"total":394.63,"count":238,"properties":[]},{"timestamp":"2019-10-04T14:00:00Z","average":1.5928151260504202,"minimum":0.89,"maximum":5.15,"total":379.09000000000003,"count":238,"properties":[]},{"timestamp":"2019-10-04T15:00:00Z","average":1.6308403361344537,"minimum":0.9,"maximum":6.63,"total":388.14,"count":238,"properties":[]},{"timestamp":"2019-10-04T16:00:00Z","average":1.6865546218487395,"minimum":0.91,"maximum":7.26,"total":401.4,"count":238,"properties":[]},{"timestamp":"2019-10-04T17:00:00Z","average":1.5926470588235295,"minimum":0.92,"maximum":6.3,"total":379.05,"count":238,"properties":[]},{"timestamp":"2019-10-04T18:00:00Z","average":1.6425210084033612,"minimum":0.96,"maximum":7.05,"total":390.91999999999996,"count":238,"properties":[]},{"timestamp":"2019-10-04T19:00:00Z","average":2.9786610878661088,"minimum":0.92,"maximum":84.66,"total":711.9,"count":239,"properties":[]},{"timestamp":"2019-10-04T20:00:00Z","average":1.6139075630252102,"minimum":0.97,"maximum":5.08,"total":384.11,"count":238,"properties":[]},{"timestamp":"2019-10-04T21:00:00Z","average":2.4130252100840335,"minimum":1.01,"maximum":41.73,"total":574.3,"count":238,"properties":[]},{"timestamp":"2019-10-04T22:00:00Z","average":1.687489539748954,"minimum":0.97,"maximum":6.28,"total":403.31,"count":239,"properties":[]},{"timestamp":"2019-10-04T23:00:00Z","average":1.6544957983193276,"minimum":0.97,"maximum":5.91,"total":393.77,"count":238,"properties":[]},{"timestamp":"2019-10-05T00:00:00Z","average":1.6677731092436976,"minimum":0.97,"maximum":8.05,"total":396.93,"count":238,"properties":[]},{"timestamp":"2019-10-05T01:00:00Z","average":1.6181932773109244,"minimum":0.97,"maximum":5.2,"total":385.13,"count":238,"properties":[]},{"timestamp":"2019-10-05T02:00:00Z","average":1.6618067226890756,"minimum":0.94,"maximum":6.8,"total":395.51,"count":238,"properties":[]},{"timestamp":"2019-10-05T03:00:00Z","average":1.6991176470588234,"minimum":1.0,"maximum":9.54,"total":404.39,"count":238,"properties":[]},{"timestamp":"2019-10-05T04:00:00Z","average":1.5654852320675106,"minimum":0.92,"maximum":6.23,"total":371.02,"count":237,"properties":[]},{"timestamp":"2019-10-05T05:00:00Z","average":1.6407531380753138,"minimum":0.9,"maximum":8.24,"total":392.14,"count":239,"properties":[]},{"timestamp":"2019-10-05T06:00:00Z","average":1.6869327731092438,"minimum":0.99,"maximum":6.43,"total":401.49,"count":238,"properties":[]},{"timestamp":"2019-10-05T07:00:00Z","average":1.648529411764706,"minimum":0.93,"maximum":7.24,"total":392.35,"count":238,"properties":[]},{"timestamp":"2019-10-05T08:00:00Z","average":1.6777731092436974,"minimum":0.93,"maximum":8.18,"total":399.31,"count":238,"properties":[]},{"timestamp":"2019-10-05T09:00:00Z","average":1.6645188284518828,"minimum":0.93,"maximum":6.69,"total":397.82,"count":239,"properties":[]},{"timestamp":"2019-10-05T10:00:00Z","average":1.5370588235294118,"minimum":0.97,"maximum":5.24,"total":365.82,"count":238,"properties":[]},{"timestamp":"2019-10-05T11:00:00Z","average":1.6972268907563026,"minimum":0.92,"maximum":6.63,"total":403.94,"count":238,"properties":[]},{"timestamp":"2019-10-05T12:00:00Z","average":1.6908823529411765,"minimum":0.96,"maximum":6.74,"total":402.43,"count":238,"properties":[]},{"timestamp":"2019-10-05T13:00:00Z","average":1.6435294117647057,"minimum":0.94,"maximum":6.54,"total":391.15999999999997,"count":238,"properties":[]},{"timestamp":"2019-10-05T14:00:00Z","average":1.5396218487394959,"minimum":0.97,"maximum":7.33,"total":366.43,"count":238,"properties":[]},{"timestamp":"2019-10-05T15:00:00Z","average":1.5672689075630253,"minimum":1.02,"maximum":7.16,"total":373.01,"count":238,"properties":[]},{"timestamp":"2019-10-05T16:00:00Z","average":1.6232217573221759,"minimum":0.99,"maximum":6.86,"total":387.95000000000005,"count":239,"properties":[]},{"timestamp":"2019-10-05T17:00:00Z","average":1.570672268907563,"minimum":1.01,"maximum":6.18,"total":373.82,"count":238,"properties":[]},{"timestamp":"2019-10-05T18:00:00Z","average":1.6340336134453781,"minimum":1.04,"maximum":7.67,"total":388.9,"count":238,"properties":[]},{"timestamp":"2019-10-05T19:00:00Z","average":1.6260504201680672,"minimum":0.99,"maximum":8.46,"total":387.0,"count":238,"properties":[]},{"timestamp":"2019-10-05T20:00:00Z","average":1.76836820083682,"minimum":1.0,"maximum":6.81,"total":422.64,"count":239,"properties":[]},{"timestamp":"2019-10-05T21:00:00Z","average":1.6063025210084032,"minimum":0.99,"maximum":6.65,"total":382.29999999999995,"count":238,"properties":[]},{"timestamp":"2019-10-05T22:00:00Z","average":1.6361344537815126,"minimum":1.0,"maximum":9.45,"total":389.4,"count":238,"properties":[]},{"timestamp":"2019-10-05T23:00:00Z","average":1.680672268907563,"minimum":0.97,"maximum":6.74,"total":400.0,"count":238,"properties":[]},{"timestamp":"2019-10-06T00:00:00Z","average":1.5763445378151262,"minimum":1.02,"maximum":5.18,"total":375.17,"count":238,"properties":[]},{"timestamp":"2019-10-06T01:00:00Z","average":1.6013025210084033,"minimum":1.0,"maximum":6.55,"total":381.11,"count":238,"properties":[]},{"timestamp":"2019-10-06T02:00:00Z","average":1.5978571428571426,"minimum":1.01,"maximum":10.26,"total":380.28999999999996,"count":238,"properties":[]},{"timestamp":"2019-10-06T03:00:00Z","average":1.61672268907563,"minimum":0.98,"maximum":6.88,"total":384.78,"count":238,"properties":[]},{"timestamp":"2019-10-06T04:00:00Z","average":1.5703765690376572,"minimum":1.0,"maximum":6.6,"total":375.32000000000005,"count":239,"properties":[]},{"timestamp":"2019-10-06T05:00:00Z","average":1.5967647058823529,"minimum":1.01,"maximum":6.82,"total":380.03,"count":238,"properties":[]},{"timestamp":"2019-10-06T06:00:00Z","average":1.6411764705882355,"minimum":1.05,"maximum":6.59,"total":390.6,"count":238,"properties":[]},{"timestamp":"2019-10-06T07:00:00Z","average":1.6069747899159665,"minimum":1.06,"maximum":6.67,"total":382.46000000000004,"count":238,"properties":[]},{"timestamp":"2019-10-06T08:00:00Z","average":1.5315899581589956,"minimum":1.03,"maximum":5.19,"total":366.04999999999995,"count":239,"properties":[]},{"timestamp":"2019-10-06T09:00:00Z","average":1.5715966386554621,"minimum":1.03,"maximum":9.08,"total":374.03999999999996,"count":238,"properties":[]},{"timestamp":"2019-10-06T10:00:00Z","average":1.5843277310924371,"minimum":1.04,"maximum":7.01,"total":377.07000000000005,"count":238,"properties":[]},{"timestamp":"2019-10-06T11:00:00Z","average":1.6245798319327731,"minimum":0.99,"maximum":6.78,"total":386.65,"count":238,"properties":[]},{"timestamp":"2019-10-06T12:00:00Z","average":1.6573529411764705,"minimum":1.03,"maximum":6.33,"total":394.45,"count":238,"properties":[]},{"timestamp":"2019-10-06T13:00:00Z","average":1.5347058823529411,"minimum":0.97,"maximum":5.21,"total":365.26,"count":238,"properties":[]},{"timestamp":"2019-10-06T14:00:00Z","average":1.5703781512605042,"minimum":0.98,"maximum":7.27,"total":373.75,"count":238,"properties":[]},{"timestamp":"2019-10-06T15:00:00Z","average":1.6546443514644351,"minimum":1.02,"maximum":5.22,"total":395.46,"count":239,"properties":[]},{"timestamp":"2019-10-06T16:00:00Z","average":1.6971848739495798,"minimum":1.03,"maximum":7.1,"total":403.93,"count":238,"properties":[]},{"timestamp":"2019-10-06T17:00:00Z","average":1.6220588235294118,"minimum":0.98,"maximum":7.56,"total":386.05,"count":238,"properties":[]},{"timestamp":"2019-10-06T18:00:00Z","average":1.7826778242677821,"minimum":1.01,"maximum":7.04,"total":426.05999999999995,"count":239,"properties":[]},{"timestamp":"2019-10-06T19:00:00Z","average":1.5249579831932776,"minimum":1.01,"maximum":6.68,"total":362.94000000000005,"count":238,"properties":[]},{"timestamp":"2019-10-06T20:00:00Z","average":1.645294117647059,"minimum":1.01,"maximum":10.3,"total":391.58000000000004,"count":238,"properties":[]},{"timestamp":"2019-10-06T21:00:00Z","average":1.4982352941176473,"minimum":0.93,"maximum":5.37,"total":356.58000000000004,"count":238,"properties":[]},{"timestamp":"2019-10-06T22:00:00Z","average":1.5023949579831932,"minimum":0.91,"maximum":7.19,"total":357.57,"count":238,"properties":[]},{"timestamp":"2019-10-06T23:00:00Z","average":1.5547698744769876,"minimum":0.89,"maximum":6.29,"total":371.59000000000003,"count":239,"properties":[]},{"timestamp":"2019-10-07T00:00:00Z","average":1.6057983193277312,"minimum":0.98,"maximum":8.95,"total":382.18,"count":238,"properties":[]},{"timestamp":"2019-10-07T01:00:00Z","average":1.6122689075630254,"minimum":0.94,"maximum":6.75,"total":383.72,"count":238,"properties":[]},{"timestamp":"2019-10-07T02:00:00Z","average":1.6401260504201682,"minimum":1.05,"maximum":8.35,"total":390.35,"count":238,"properties":[]},{"timestamp":"2019-10-07T03:00:00Z","average":1.5948319327731095,"minimum":1.04,"maximum":6.8,"total":379.57000000000005,"count":238,"properties":[]},{"timestamp":"2019-10-07T04:00:00Z","average":1.6135294117647059,"minimum":0.99,"maximum":6.57,"total":384.02,"count":238,"properties":[]},{"timestamp":"2019-10-07T05:00:00Z","average":1.6213807531380753,"minimum":1.04,"maximum":6.35,"total":387.51,"count":239,"properties":[]},{"timestamp":"2019-10-07T06:00:00Z","average":1.5760084033613446,"minimum":1.02,"maximum":6.63,"total":375.09000000000003,"count":238,"properties":[]},{"timestamp":"2019-10-07T07:00:00Z","average":1.6268067226890754,"minimum":1.0,"maximum":6.85,"total":387.17999999999995,"count":238,"properties":[]},{"timestamp":"2019-10-07T08:00:00Z","average":1.6779411764705883,"minimum":1.01,"maximum":7.78,"total":399.35,"count":238,"properties":[]},{"timestamp":"2019-10-07T09:00:00Z","average":1.572563025210084,"minimum":1.01,"maximum":6.33,"total":374.27,"count":238,"properties":[]},{"timestamp":"2019-10-07T10:00:00Z","average":1.6275630252100841,"minimum":1.03,"maximum":7.76,"total":387.36,"count":238,"properties":[]},{"timestamp":"2019-10-07T11:00:00Z","average":1.5733054393305439,"minimum":1.04,"maximum":5.5,"total":376.02,"count":239,"properties":[]},{"timestamp":"2019-10-07T12:00:00Z","average":1.5771428571428572,"minimum":1.03,"maximum":5.44,"total":375.36,"count":238,"properties":[]},{"timestamp":"2019-10-07T13:00:00Z","average":1.5830672268907562,"minimum":1.05,"maximum":7.06,"total":376.77,"count":238,"properties":[]},{"timestamp":"2019-10-07T14:00:00Z","average":1.5254621848739496,"minimum":0.99,"maximum":6.37,"total":363.06,"count":238,"properties":[]},{"timestamp":"2019-10-07T15:00:00Z","average":1.6413025210084033,"minimum":1.03,"maximum":5.08,"total":390.63,"count":238,"properties":[]},{"timestamp":"2019-10-07T16:00:00Z","average":1.9149159663865547,"minimum":1.07,"maximum":20.16,"total":455.75,"count":238,"properties":[]},{"timestamp":"2019-10-07T17:00:00Z","average":1.5486192468619246,"minimum":1.08,"maximum":6.39,"total":370.12,"count":239,"properties":[]},{"timestamp":"2019-10-07T18:00:00Z","average":2.0477731092436975,"minimum":1.07,"maximum":22.59,"total":487.37,"count":238,"properties":[]},{"timestamp":"2019-10-07T19:00:00Z","average":1.6536974789915968,"minimum":1.07,"maximum":5.62,"total":393.58000000000004,"count":238,"properties":[]},{"timestamp":"2019-10-07T20:00:00Z","average":1.6092016806722689,"minimum":1.02,"maximum":7.15,"total":382.99,"count":238,"properties":[]},{"timestamp":"2019-10-07T21:00:00Z","average":1.5750000000000002,"minimum":1.04,"maximum":5.16,"total":374.85,"count":238,"properties":[]},{"timestamp":"2019-10-07T22:00:00Z","average":1.7382008368200836,"minimum":1.03,"maximum":9.6,"total":415.43,"count":239,"properties":[]},{"timestamp":"2019-10-07T23:00:00Z","average":1.6205462184873951,"minimum":0.97,"maximum":7.77,"total":385.69000000000005,"count":238,"properties":[]},{"timestamp":"2019-10-08T00:00:00Z","average":1.493781512605042,"minimum":0.93,"maximum":6.02,"total":355.52,"count":238,"properties":[]},{"timestamp":"2019-10-08T01:00:00Z","average":1.5010084033613447,"minimum":0.89,"maximum":6.03,"total":357.24,"count":238,"properties":[]},{"timestamp":"2019-10-08T02:00:00Z","average":1.4615966386554622,"minimum":0.91,"maximum":5.17,"total":347.86,"count":238,"properties":[]},{"timestamp":"2019-10-08T03:00:00Z","average":1.5447698744769873,"minimum":0.92,"maximum":8.36,"total":369.2,"count":239,"properties":[]},{"timestamp":"2019-10-08T04:00:00Z","average":1.6713865546218489,"minimum":1.05,"maximum":7.09,"total":397.79,"count":238,"properties":[]},{"timestamp":"2019-10-08T05:00:00Z","average":1.5673109243697478,"minimum":1.0,"maximum":7.56,"total":373.02,"count":238,"properties":[]},{"timestamp":"2019-10-08T06:00:00Z","average":1.5813025210084035,"minimum":0.91,"maximum":5.44,"total":376.35,"count":238,"properties":[]},{"timestamp":"2019-10-08T07:00:00Z","average":2.2375,"minimum":1.18,"maximum":4.32,"total":8.95,"count":4,"properties":[]}],"resourceId":null,"properties":[],"id":"/subscriptions/bbd83110-10a9-4d2f-9b08-ec69f129c56b/resourceGroups/webflowersproductcentral/providers/Microsoft.ClassicCompute/domainNames/webflowersproductcentral/slots/Production/roles/GloboStudio.Core.WebServices/metrics/Percentage CPU"},{"name":{"value":"Network In","localizedValue":"Network In"},"unit":"Bytes","timeGrain":"PT1H","startTime":"2019-10-01T15:00:00Z","endTime":"2019-10-08T07:00:00Z","metricValues":[{"timestamp":"2019-10-01T15:00:00Z","average":100.85013888888889,"minimum":0.0,"maximum":55388.0,"total":726121.0,"count":7200,"properties":[]},{"timestamp":"2019-10-01T16:00:00Z","average":90.67875,"minimum":0.0,"maximum":18146.0,"total":652887.0,"count":7200,"properties":[]},{"timestamp":"2019-10-01T17:00:00Z","average":96.351805555555558,"minimum":0.0,"maximum":18964.0,"total":693733.0,"count":7200,"properties":[]},{"timestamp":"2019-10-01T18:00:00Z","average":112.66902777777777,"minimum":0.0,"maximum":50475.0,"total":811217.0,"count":7200,"properties":[]},{"timestamp":"2019-10-01T19:00:00Z","average":105.95180555555555,"minimum":0.0,"maximum":28927.0,"total":762853.0,"count":7200,"properties":[]},{"timestamp":"2019-10-01T20:00:00Z","average":99.3775,"minimum":0.0,"maximum":24509.0,"total":715518.0,"count":7200,"properties":[]},{"timestamp":"2019-10-01T21:00:00Z","average":172.23583333333335,"minimum":0.0,"maximum":280902.0,"total":1240098.0,"count":7200,"properties":[]},{"timestamp":"2019-10-01T22:00:00Z","average":90.742638888888891,"minimum":0.0,"maximum":16414.0,"total":653347.0,"count":7200,"properties":[]},{"timestamp":"2019-10-01T23:00:00Z","average":89.956805555555562,"minimum":0.0,"maximum":16546.0,"total":647689.0,"count":7200,"properties":[]},{"timestamp":"2019-10-02T00:00:00Z","average":115.09166666666667,"minimum":0.0,"maximum":71622.0,"total":828660.0,"count":7200,"properties":[]},{"timestamp":"2019-10-02T01:00:00Z","average":95.110138888888883,"minimum":0.0,"maximum":29023.0,"total":684793.0,"count":7200,"properties":[]},{"timestamp":"2019-10-02T02:00:00Z","average":97.3476388888889,"minimum":0.0,"maximum":19073.0,"total":700903.0,"count":7200,"properties":[]},{"timestamp":"2019-10-02T03:00:00Z","average":99.2936111111111,"minimum":0.0,"maximum":27148.0,"total":714914.0,"count":7200,"properties":[]},{"timestamp":"2019-10-02T04:00:00Z","average":89.926111111111112,"minimum":0.0,"maximum":16540.0,"total":647468.0,"count":7200,"properties":[]},{"timestamp":"2019-10-02T05:00:00Z","average":98.858472222222218,"minimum":0.0,"maximum":28927.0,"total":711781.0,"count":7200,"properties":[]},{"timestamp":"2019-10-02T06:00:00Z","average":96.185,"minimum":0.0,"maximum":19258.0,"total":692532.0,"count":7200,"properties":[]},{"timestamp":"2019-10-02T07:00:00Z","average":93.93805555555555,"minimum":0.0,"maximum":27667.0,"total":676354.0,"count":7200,"properties":[]},{"timestamp":"2019-10-02T08:00:00Z","average":112.90097222222222,"minimum":0.0,"maximum":66391.0,"total":812887.0,"count":7200,"properties":[]},{"timestamp":"2019-10-02T09:00:00Z","average":97.180972222222223,"minimum":0.0,"maximum":27088.0,"total":699703.0,"count":7200,"properties":[]},{"timestamp":"2019-10-02T10:00:00Z","average":97.525555555555556,"minimum":0.0,"maximum":18964.0,"total":702184.0,"count":7200,"properties":[]},{"timestamp":"2019-10-02T11:00:00Z","average":99.643472222222229,"minimum":0.0,"maximum":24219.0,"total":717433.0,"count":7200,"properties":[]},{"timestamp":"2019-10-02T12:00:00Z","average":204.90180555555557,"minimum":0.0,"maximum":193536.0,"total":1475293.0,"count":7200,"properties":[]},{"timestamp":"2019-10-02T13:00:00Z","average":170.37625,"minimum":0.0,"maximum":235839.0,"total":1226709.0,"count":7200,"properties":[]},{"timestamp":"2019-10-02T14:00:00Z","average":98.555555555555557,"minimum":0.0,"maximum":29406.0,"total":709600.0,"count":7200,"properties":[]},{"timestamp":"2019-10-02T15:00:00Z","average":95.217083333333335,"minimum":0.0,"maximum":27158.0,"total":685563.0,"count":7200,"properties":[]},{"timestamp":"2019-10-02T16:00:00Z","average":94.375277777777782,"minimum":0.0,"maximum":19483.0,"total":679502.0,"count":7200,"properties":[]},{"timestamp":"2019-10-02T17:00:00Z","average":109.96888888888888,"minimum":0.0,"maximum":27287.0,"total":791776.0,"count":7200,"properties":[]},{"timestamp":"2019-10-02T18:00:00Z","average":122.11361111111111,"minimum":0.0,"maximum":29116.0,"total":879218.0,"count":7200,"properties":[]},{"timestamp":"2019-10-02T19:00:00Z","average":119.06194444444445,"minimum":0.0,"maximum":29271.0,"total":857246.0,"count":7200,"properties":[]},{"timestamp":"2019-10-02T20:00:00Z","average":114.56819444444444,"minimum":0.0,"maximum":27287.0,"total":824891.0,"count":7200,"properties":[]},{"timestamp":"2019-10-02T21:00:00Z","average":113.57986111111111,"minimum":0.0,"maximum":28911.0,"total":817775.0,"count":7200,"properties":[]},{"timestamp":"2019-10-02T22:00:00Z","average":117.63180555555556,"minimum":0.0,"maximum":29132.0,"total":846949.0,"count":7200,"properties":[]},{"timestamp":"2019-10-02T23:00:00Z","average":115.87527777777778,"minimum":0.0,"maximum":16373.0,"total":834302.0,"count":7200,"properties":[]},{"timestamp":"2019-10-03T00:00:00Z","average":116.18638888888889,"minimum":0.0,"maximum":29132.0,"total":836542.0,"count":7200,"properties":[]},{"timestamp":"2019-10-03T01:00:00Z","average":111.04583333333333,"minimum":0.0,"maximum":16764.0,"total":799530.0,"count":7200,"properties":[]},{"timestamp":"2019-10-03T02:00:00Z","average":115.94694444444444,"minimum":0.0,"maximum":16764.0,"total":834818.0,"count":7200,"properties":[]},{"timestamp":"2019-10-03T03:00:00Z","average":113.38138888888889,"minimum":0.0,"maximum":27607.0,"total":816346.0,"count":7200,"properties":[]},{"timestamp":"2019-10-03T04:00:00Z","average":120.83263888888889,"minimum":0.0,"maximum":50117.0,"total":869995.0,"count":7200,"properties":[]},{"timestamp":"2019-10-03T05:00:00Z","average":113.63347222222222,"minimum":0.0,"maximum":27287.0,"total":818161.0,"count":7200,"properties":[]},{"timestamp":"2019-10-03T06:00:00Z","average":106.30444444444444,"minimum":0.0,"maximum":19318.0,"total":765392.0,"count":7200,"properties":[]},{"timestamp":"2019-10-03T07:00:00Z","average":116.49416666666667,"minimum":0.0,"maximum":29132.0,"total":838758.0,"count":7200,"properties":[]},{"timestamp":"2019-10-03T08:00:00Z","average":115.19180555555556,"minimum":0.0,"maximum":18964.0,"total":829381.0,"count":7200,"properties":[]},{"timestamp":"2019-10-03T09:00:00Z","average":123.08541666666666,"minimum":0.0,"maximum":66046.0,"total":886215.0,"count":7200,"properties":[]},{"timestamp":"2019-10-03T10:00:00Z","average":112.82152777777777,"minimum":0.0,"maximum":28927.0,"total":812315.0,"count":7200,"properties":[]},{"timestamp":"2019-10-03T11:00:00Z","average":127.68541666666667,"minimum":0.0,"maximum":71292.0,"total":919335.0,"count":7200,"properties":[]},{"timestamp":"2019-10-03T12:00:00Z","average":120.32263888888889,"minimum":0.0,"maximum":55032.0,"total":866323.0,"count":7200,"properties":[]},{"timestamp":"2019-10-03T13:00:00Z","average":109.07597222222222,"minimum":0.0,"maximum":26722.0,"total":785347.0,"count":7200,"properties":[]},{"timestamp":"2019-10-03T14:00:00Z","average":127.93138888888889,"minimum":0.0,"maximum":54972.0,"total":921106.0,"count":7200,"properties":[]},{"timestamp":"2019-10-03T15:00:00Z","average":113.91208333333333,"minimum":0.0,"maximum":27072.0,"total":820167.0,"count":7200,"properties":[]},{"timestamp":"2019-10-03T16:00:00Z","average":101.90291666666667,"minimum":0.0,"maximum":26858.0,"total":733701.0,"count":7200,"properties":[]},{"timestamp":"2019-10-03T17:00:00Z","average":125.33097222222223,"minimum":0.0,"maximum":55032.0,"total":902383.0,"count":7200,"properties":[]},{"timestamp":"2019-10-03T18:00:00Z","average":123.15805555555555,"minimum":0.0,"maximum":29132.0,"total":886738.0,"count":7200,"properties":[]},{"timestamp":"2019-10-03T19:00:00Z","average":120.12708333333333,"minimum":0.0,"maximum":27607.0,"total":864915.0,"count":7200,"properties":[]},{"timestamp":"2019-10-03T20:00:00Z","average":114.06135057471265,"minimum":0.0,"maximum":49716.0,"total":793867.0,"count":6960,"properties":[]},{"timestamp":"2019-10-03T21:00:00Z","average":8659.4836134453781,"minimum":0.0,"maximum":60692723.0,"total":61828713.0,"count":7140,"properties":[]},{"timestamp":"2019-10-03T22:00:00Z","average":160.00367231638418,"minimum":0.0,"maximum":29132.0,"total":1132826.0,"count":7080,"properties":[]},{"timestamp":"2019-10-03T23:00:00Z","average":115.92111111111112,"minimum":0.0,"maximum":28911.0,"total":834632.0,"count":7200,"properties":[]},{"timestamp":"2019-10-04T00:00:00Z","average":107.52791666666667,"minimum":0.0,"maximum":16373.0,"total":774201.0,"count":7200,"properties":[]},{"timestamp":"2019-10-04T01:00:00Z","average":113.60708333333334,"minimum":0.0,"maximum":27088.0,"total":817971.0,"count":7200,"properties":[]},{"timestamp":"2019-10-04T02:00:00Z","average":113.21972222222222,"minimum":0.0,"maximum":28927.0,"total":815182.0,"count":7200,"properties":[]},{"timestamp":"2019-10-04T03:00:00Z","average":136.83041666666668,"minimum":0.0,"maximum":70856.0,"total":985179.00000000012,"count":7200,"properties":[]},{"timestamp":"2019-10-04T04:00:00Z","average":121.44791666666667,"minimum":0.0,"maximum":27088.0,"total":874425.0,"count":7200,"properties":[]},{"timestamp":"2019-10-04T05:00:00Z","average":114.89166666666667,"minimum":0.0,"maximum":27547.0,"total":827220.0,"count":7200,"properties":[]},{"timestamp":"2019-10-04T06:00:00Z","average":112.23847222222223,"minimum":0.0,"maximum":27148.0,"total":808117.0,"count":7200,"properties":[]},{"timestamp":"2019-10-04T07:00:00Z","average":107.53986111111111,"minimum":0.0,"maximum":28927.0,"total":774287.0,"count":7200,"properties":[]},{"timestamp":"2019-10-04T08:00:00Z","average":100.55652777777777,"minimum":0.0,"maximum":16426.0,"total":724007.0,"count":7200,"properties":[]},{"timestamp":"2019-10-04T09:00:00Z","average":107.56277777777778,"minimum":0.0,"maximum":19258.0,"total":774452.0,"count":7200,"properties":[]},{"timestamp":"2019-10-04T10:00:00Z","average":109.16388888888889,"minimum":0.0,"maximum":55446.0,"total":785980.0,"count":7200,"properties":[]},{"timestamp":"2019-10-04T11:00:00Z","average":103.95,"minimum":0.0,"maximum":26722.0,"total":748440.0,"count":7200,"properties":[]},{"timestamp":"2019-10-04T12:00:00Z","average":95.652777777777771,"minimum":0.0,"maximum":16540.0,"total":688700.0,"count":7200,"properties":[]},{"timestamp":"2019-10-04T13:00:00Z","average":106.42555555555556,"minimum":0.0,"maximum":26678.0,"total":766264.0,"count":7200,"properties":[]},{"timestamp":"2019-10-04T14:00:00Z","average":94.84319444444445,"minimum":0.0,"maximum":16414.0,"total":682871.0,"count":7200,"properties":[]},{"timestamp":"2019-10-04T15:00:00Z","average":100.24888888888889,"minimum":0.0,"maximum":27173.0,"total":721792.0,"count":7200,"properties":[]},{"timestamp":"2019-10-04T16:00:00Z","average":116.39736111111111,"minimum":0.0,"maximum":55141.0,"total":838061.0,"count":7200,"properties":[]},{"timestamp":"2019-10-04T17:00:00Z","average":100.15430555555555,"minimum":0.0,"maximum":27148.0,"total":721111.0,"count":7200,"properties":[]},{"timestamp":"2019-10-04T18:00:00Z","average":99.933333333333337,"minimum":0.0,"maximum":24137.0,"total":719520.0,"count":7200,"properties":[]},{"timestamp":"2019-10-04T19:00:00Z","average":190.50069444444443,"minimum":0.0,"maximum":309731.0,"total":1371605.0,"count":7200,"properties":[]},{"timestamp":"2019-10-04T20:00:00Z","average":97.6451388888889,"minimum":0.0,"maximum":16373.0,"total":703045.0,"count":7200,"properties":[]},{"timestamp":"2019-10-04T21:00:00Z","average":397.73444444444442,"minimum":0.0,"maximum":245126.0,"total":2863688.0,"count":7200,"properties":[]},{"timestamp":"2019-10-04T22:00:00Z","average":100.69208333333333,"minimum":0.0,"maximum":27148.0,"total":724983.0,"count":7200,"properties":[]},{"timestamp":"2019-10-04T23:00:00Z","average":99.076666666666668,"minimum":0.0,"maximum":19038.0,"total":713352.0,"count":7200,"properties":[]},{"timestamp":"2019-10-05T00:00:00Z","average":107.21763888888889,"minimum":0.0,"maximum":71621.0,"total":771967.0,"count":7200,"properties":[]},{"timestamp":"2019-10-05T01:00:00Z","average":96.1675,"minimum":0.0,"maximum":22399.0,"total":692406.0,"count":7200,"properties":[]},{"timestamp":"2019-10-05T02:00:00Z","average":96.2311111111111,"minimum":0.0,"maximum":29233.0,"total":692864.0,"count":7200,"properties":[]},{"timestamp":"2019-10-05T03:00:00Z","average":104.89291666666666,"minimum":0.0,"maximum":19788.0,"total":755229.0,"count":7200,"properties":[]},{"timestamp":"2019-10-05T04:00:00Z","average":96.758055555555558,"minimum":0.0,"maximum":19103.0,"total":696658.0,"count":7200,"properties":[]},{"timestamp":"2019-10-05T05:00:00Z","average":101.06,"minimum":0.0,"maximum":19103.0,"total":727632.0,"count":7200,"properties":[]},{"timestamp":"2019-10-05T06:00:00Z","average":103.13708333333334,"minimum":0.0,"maximum":29050.0,"total":742587.0,"count":7200,"properties":[]},{"timestamp":"2019-10-05T07:00:00Z","average":94.863194444444446,"minimum":0.0,"maximum":27148.0,"total":683015.0,"count":7200,"properties":[]},{"timestamp":"2019-10-05T08:00:00Z","average":92.369583333333338,"minimum":0.0,"maximum":18693.0,"total":665061.0,"count":7200,"properties":[]},{"timestamp":"2019-10-05T09:00:00Z","average":107.7825,"minimum":0.0,"maximum":27336.0,"total":776034.0,"count":7200,"properties":[]},{"timestamp":"2019-10-05T10:00:00Z","average":94.1836111111111,"minimum":0.0,"maximum":19087.0,"total":678122.0,"count":7200,"properties":[]},{"timestamp":"2019-10-05T11:00:00Z","average":103.7275,"minimum":0.0,"maximum":27148.0,"total":746838.0,"count":7200,"properties":[]},{"timestamp":"2019-10-05T12:00:00Z","average":102.50527777777778,"minimum":0.0,"maximum":29132.0,"total":738038.0,"count":7200,"properties":[]},{"timestamp":"2019-10-05T13:00:00Z","average":100.15833333333333,"minimum":0.0,"maximum":19038.0,"total":721140.0,"count":7200,"properties":[]},{"timestamp":"2019-10-05T14:00:00Z","average":94.583472222222227,"minimum":0.0,"maximum":28510.0,"total":681001.0,"count":7200,"properties":[]},{"timestamp":"2019-10-05T15:00:00Z","average":105.16958333333334,"minimum":0.0,"maximum":54977.0,"total":757221.0,"count":7200,"properties":[]},{"timestamp":"2019-10-05T16:00:00Z","average":101.83013888888888,"minimum":0.0,"maximum":26738.0,"total":733177.0,"count":7200,"properties":[]},{"timestamp":"2019-10-05T17:00:00Z","average":98.107222222222219,"minimum":0.0,"maximum":27132.0,"total":706372.0,"count":7200,"properties":[]},{"timestamp":"2019-10-05T18:00:00Z","average":102.63027777777778,"minimum":0.0,"maximum":27197.0,"total":738938.0,"count":7200,"properties":[]},{"timestamp":"2019-10-05T19:00:00Z","average":103.03055555555555,"minimum":0.0,"maximum":29319.0,"total":741820.0,"count":7200,"properties":[]},{"timestamp":"2019-10-05T20:00:00Z","average":99.16875,"minimum":0.0,"maximum":27132.0,"total":714015.0,"count":7200,"properties":[]},{"timestamp":"2019-10-05T21:00:00Z","average":96.120138888888889,"minimum":0.0,"maximum":19978.0,"total":692065.0,"count":7200,"properties":[]},{"timestamp":"2019-10-05T22:00:00Z","average":99.39180555555555,"minimum":0.0,"maximum":29271.0,"total":715621.0,"count":7200,"properties":[]},{"timestamp":"2019-10-05T23:00:00Z","average":136.42347222222222,"minimum":0.0,"maximum":26738.0,"total":982249.0,"count":7200,"properties":[]},{"timestamp":"2019-10-06T00:00:00Z","average":98.484166666666667,"minimum":0.0,"maximum":27377.0,"total":709086.0,"count":7200,"properties":[]},{"timestamp":"2019-10-06T01:00:00Z","average":100.57138888888889,"minimum":0.0,"maximum":29356.0,"total":724114.0,"count":7200,"properties":[]},{"timestamp":"2019-10-06T02:00:00Z","average":103.58861111111111,"minimum":0.0,"maximum":27607.0,"total":745838.0,"count":7200,"properties":[]},{"timestamp":"2019-10-06T03:00:00Z","average":107.33069444444445,"minimum":0.0,"maximum":29066.0,"total":772781.0,"count":7200,"properties":[]},{"timestamp":"2019-10-06T04:00:00Z","average":97.127083333333331,"minimum":0.0,"maximum":19177.0,"total":699315.0,"count":7200,"properties":[]},{"timestamp":"2019-10-06T05:00:00Z","average":98.325972222222219,"minimum":0.0,"maximum":19013.0,"total":707947.0,"count":7200,"properties":[]},{"timestamp":"2019-10-06T06:00:00Z","average":106.19486111111111,"minimum":0.0,"maximum":27268.0,"total":764603.0,"count":7200,"properties":[]},{"timestamp":"2019-10-06T07:00:00Z","average":107.73680555555555,"minimum":0.0,"maximum":54972.0,"total":775705.0,"count":7200,"properties":[]},{"timestamp":"2019-10-06T08:00:00Z","average":90.73375,"minimum":0.0,"maximum":18206.0,"total":653283.0,"count":7200,"properties":[]},{"timestamp":"2019-10-06T09:00:00Z","average":97.779305555555553,"minimum":0.0,"maximum":27591.0,"total":704011.0,"count":7200,"properties":[]},{"timestamp":"2019-10-06T10:00:00Z","average":96.904722222222219,"minimum":0.0,"maximum":29162.0,"total":697714.0,"count":7200,"properties":[]},{"timestamp":"2019-10-06T11:00:00Z","average":128.07430555555555,"minimum":0.0,"maximum":55038.0,"total":922135.0,"count":7200,"properties":[]},{"timestamp":"2019-10-06T12:00:00Z","average":134.69263888888889,"minimum":0.0,"maximum":27257.0,"total":969787.0,"count":7200,"properties":[]},{"timestamp":"2019-10-06T13:00:00Z","average":93.665,"minimum":0.0,"maximum":19163.0,"total":674388.0,"count":7200,"properties":[]},{"timestamp":"2019-10-06T14:00:00Z","average":91.6525,"minimum":0.0,"maximum":16426.0,"total":659898.0,"count":7200,"properties":[]},{"timestamp":"2019-10-06T15:00:00Z","average":116.1588888888889,"minimum":0.0,"maximum":29673.0,"total":836344.0,"count":7200,"properties":[]},{"timestamp":"2019-10-06T16:00:00Z","average":184.94708333333332,"minimum":0.0,"maximum":54812.0,"total":1331619.0,"count":7200,"properties":[]},{"timestamp":"2019-10-06T17:00:00Z","average":113.03861111111111,"minimum":0.0,"maximum":71196.0,"total":813878.0,"count":7200,"properties":[]},{"timestamp":"2019-10-06T18:00:00Z","average":99.768055555555549,"minimum":0.0,"maximum":26738.0,"total":718330.0,"count":7200,"properties":[]},{"timestamp":"2019-10-06T19:00:00Z","average":99.139583333333334,"minimum":0.0,"maximum":55453.0,"total":713805.0,"count":7200,"properties":[]},{"timestamp":"2019-10-06T20:00:00Z","average":107.90236111111111,"minimum":0.0,"maximum":71729.0,"total":776897.0,"count":7200,"properties":[]},{"timestamp":"2019-10-06T21:00:00Z","average":105.53416666666666,"minimum":0.0,"maximum":27555.0,"total":759846.0,"count":7200,"properties":[]},{"timestamp":"2019-10-06T22:00:00Z","average":108.33930555555555,"minimum":0.0,"maximum":71212.0,"total":780043.0,"count":7200,"properties":[]},{"timestamp":"2019-10-06T23:00:00Z","average":106.24305555555556,"minimum":0.0,"maximum":27214.0,"total":764950.0,"count":7200,"properties":[]},{"timestamp":"2019-10-07T00:00:00Z","average":111.5501388888889,"minimum":0.0,"maximum":27148.0,"total":803161.0,"count":7200,"properties":[]},{"timestamp":"2019-10-07T01:00:00Z","average":108.63263888888889,"minimum":0.0,"maximum":27607.0,"total":782155.0,"count":7200,"properties":[]},{"timestamp":"2019-10-07T02:00:00Z","average":104.9175,"minimum":0.0,"maximum":28927.0,"total":755406.0,"count":7200,"properties":[]},{"timestamp":"2019-10-07T03:00:00Z","average":105.02944444444445,"minimum":0.0,"maximum":19133.0,"total":756212.0,"count":7200,"properties":[]},{"timestamp":"2019-10-07T04:00:00Z","average":102.99222222222222,"minimum":0.0,"maximum":28927.0,"total":741544.0,"count":7200,"properties":[]},{"timestamp":"2019-10-07T05:00:00Z","average":115.9348611111111,"minimum":0.0,"maximum":71621.0,"total":834731.0,"count":7200,"properties":[]},{"timestamp":"2019-10-07T06:00:00Z","average":99.12222222222222,"minimum":0.0,"maximum":18554.0,"total":713680.0,"count":7200,"properties":[]},{"timestamp":"2019-10-07T07:00:00Z","average":114.52138888888889,"minimum":0.0,"maximum":55387.0,"total":824554.0,"count":7200,"properties":[]},{"timestamp":"2019-10-07T08:00:00Z","average":114.41513888888889,"minimum":0.0,"maximum":71190.0,"total":823789.0,"count":7200,"properties":[]},{"timestamp":"2019-10-07T09:00:00Z","average":103.51444444444445,"minimum":0.0,"maximum":27148.0,"total":745304.0,"count":7200,"properties":[]},{"timestamp":"2019-10-07T10:00:00Z","average":109.91902777777777,"minimum":0.0,"maximum":27148.0,"total":791417.0,"count":7200,"properties":[]},{"timestamp":"2019-10-07T11:00:00Z","average":96.272638888888892,"minimum":0.0,"maximum":16373.0,"total":693163.0,"count":7200,"properties":[]},{"timestamp":"2019-10-07T12:00:00Z","average":98.2238888888889,"minimum":0.0,"maximum":19318.0,"total":707212.0,"count":7200,"properties":[]},{"timestamp":"2019-10-07T13:00:00Z","average":99.170833333333334,"minimum":0.0,"maximum":18628.0,"total":714030.0,"count":7200,"properties":[]},{"timestamp":"2019-10-07T14:00:00Z","average":94.810277777777785,"minimum":0.0,"maximum":16540.0,"total":682634.0,"count":7200,"properties":[]},{"timestamp":"2019-10-07T15:00:00Z","average":95.470416666666665,"minimum":0.0,"maximum":16414.0,"total":687387.0,"count":7200,"properties":[]},{"timestamp":"2019-10-07T16:00:00Z","average":175.78597222222223,"minimum":0.0,"maximum":231745.0,"total":1265659.0,"count":7200,"properties":[]},{"timestamp":"2019-10-07T17:00:00Z","average":97.06,"minimum":0.0,"maximum":29066.0,"total":698832.0,"count":7200,"properties":[]},{"timestamp":"2019-10-07T18:00:00Z","average":389.55513888888891,"minimum":0.0,"maximum":215811.0,"total":2804797.0,"count":7200,"properties":[]},{"timestamp":"2019-10-07T19:00:00Z","average":99.907222222222217,"minimum":0.0,"maximum":27833.0,"total":719332.0,"count":7200,"properties":[]},{"timestamp":"2019-10-07T20:00:00Z","average":97.258472222222224,"minimum":0.0,"maximum":16644.0,"total":700261.0,"count":7200,"properties":[]},{"timestamp":"2019-10-07T21:00:00Z","average":94.90902777777778,"minimum":0.0,"maximum":16553.0,"total":683345.0,"count":7200,"properties":[]},{"timestamp":"2019-10-07T22:00:00Z","average":106.23333333333333,"minimum":0.0,"maximum":28682.0,"total":764880.0,"count":7200,"properties":[]},{"timestamp":"2019-10-07T23:00:00Z","average":100.07597222222222,"minimum":0.0,"maximum":26738.0,"total":720547.0,"count":7200,"properties":[]},{"timestamp":"2019-10-08T00:00:00Z","average":96.563194444444449,"minimum":0.0,"maximum":27607.0,"total":695255.0,"count":7200,"properties":[]},{"timestamp":"2019-10-08T01:00:00Z","average":96.958333333333329,"minimum":0.0,"maximum":29132.0,"total":698100.0,"count":7200,"properties":[]},{"timestamp":"2019-10-08T02:00:00Z","average":92.556666666666672,"minimum":0.0,"maximum":16373.0,"total":666408.0,"count":7200,"properties":[]},{"timestamp":"2019-10-08T03:00:00Z","average":100.22777777777777,"minimum":0.0,"maximum":29361.0,"total":721640.0,"count":7200,"properties":[]},{"timestamp":"2019-10-08T04:00:00Z","average":114.06652777777778,"minimum":0.0,"maximum":55244.0,"total":821279.0,"count":7200,"properties":[]},{"timestamp":"2019-10-08T05:00:00Z","average":94.116527777777776,"minimum":0.0,"maximum":19788.0,"total":677639.0,"count":7200,"properties":[]},{"timestamp":"2019-10-08T06:00:00Z","average":98.281944444444449,"minimum":0.0,"maximum":28927.0,"total":707630.0,"count":7200,"properties":[]},{"timestamp":"2019-10-08T07:00:00Z","average":135.28333333333333,"minimum":0.0,"maximum":16234.0,"total":16234.0,"count":120,"properties":[]}],"resourceId":null,"properties":[],"id":"/subscriptions/bbd83110-10a9-4d2f-9b08-ec69f129c56b/resourceGroups/webflowersproductcentral/providers/Microsoft.ClassicCompute/domainNames/webflowersproductcentral/slots/Production/roles/GloboStudio.Core.WebServices/metrics/Network In"},{"name":{"value":"Network Out","localizedValue":"Network Out"},"unit":"Bytes","timeGrain":"PT1H","startTime":"2019-10-01T15:00:00Z","endTime":"2019-10-08T07:00:00Z","metricValues":[{"timestamp":"2019-10-01T15:00:00Z","average":94.75055555555555,"minimum":0.0,"maximum":22723.0,"total":682204.0,"count":7200,"properties":[]},{"timestamp":"2019-10-01T16:00:00Z","average":92.208194444444445,"minimum":0.0,"maximum":20641.0,"total":663899.0,"count":7200,"properties":[]},{"timestamp":"2019-10-01T17:00:00Z","average":93.535694444444445,"minimum":0.0,"maximum":17189.0,"total":673457.0,"count":7200,"properties":[]},{"timestamp":"2019-10-01T18:00:00Z","average":104.45680555555556,"minimum":0.0,"maximum":25525.0,"total":752089.0,"count":7200,"properties":[]},{"timestamp":"2019-10-01T19:00:00Z","average":103.87138888888889,"minimum":0.0,"maximum":26003.0,"total":747874.0,"count":7200,"properties":[]},{"timestamp":"2019-10-01T20:00:00Z","average":96.788055555555559,"minimum":0.0,"maximum":20936.0,"total":696874.0,"count":7200,"properties":[]},{"timestamp":"2019-10-01T21:00:00Z","average":420.56958333333336,"minimum":0.0,"maximum":1333930.0,"total":3028101.0,"count":7200,"properties":[]},{"timestamp":"2019-10-01T22:00:00Z","average":92.506666666666661,"minimum":0.0,"maximum":16797.0,"total":666048.0,"count":7200,"properties":[]},{"timestamp":"2019-10-01T23:00:00Z","average":91.362083333333331,"minimum":0.0,"maximum":18576.0,"total":657807.0,"count":7200,"properties":[]},{"timestamp":"2019-10-02T00:00:00Z","average":102.76680555555555,"minimum":0.0,"maximum":25337.0,"total":739921.0,"count":7200,"properties":[]},{"timestamp":"2019-10-02T01:00:00Z","average":93.9276388888889,"minimum":0.0,"maximum":25767.0,"total":676279.0,"count":7200,"properties":[]},{"timestamp":"2019-10-02T02:00:00Z","average":96.940416666666664,"minimum":0.0,"maximum":16919.0,"total":697971.0,"count":7200,"properties":[]},{"timestamp":"2019-10-02T03:00:00Z","average":96.602916666666673,"minimum":0.0,"maximum":22375.0,"total":695541.0,"count":7200,"properties":[]},{"timestamp":"2019-10-02T04:00:00Z","average":91.055694444444441,"minimum":0.0,"maximum":17075.0,"total":655601.0,"count":7200,"properties":[]},{"timestamp":"2019-10-02T05:00:00Z","average":97.234861111111115,"minimum":0.0,"maximum":21118.0,"total":700091.0,"count":7200,"properties":[]},{"timestamp":"2019-10-02T06:00:00Z","average":96.317083333333329,"minimum":0.0,"maximum":25427.0,"total":693483.0,"count":7200,"properties":[]},{"timestamp":"2019-10-02T07:00:00Z","average":93.0423611111111,"minimum":0.0,"maximum":22307.0,"total":669905.0,"count":7200,"properties":[]},{"timestamp":"2019-10-02T08:00:00Z","average":103.15805555555555,"minimum":0.0,"maximum":24245.0,"total":742738.0,"count":7200,"properties":[]},{"timestamp":"2019-10-02T09:00:00Z","average":95.844861111111115,"minimum":0.0,"maximum":22283.0,"total":690083.0,"count":7200,"properties":[]},{"timestamp":"2019-10-02T10:00:00Z","average":94.7175,"minimum":0.0,"maximum":21118.0,"total":681966.0,"count":7200,"properties":[]},{"timestamp":"2019-10-02T11:00:00Z","average":95.068194444444444,"minimum":0.0,"maximum":19950.0,"total":684491.0,"count":7200,"properties":[]},{"timestamp":"2019-10-02T12:00:00Z","average":463.46486111111113,"minimum":0.0,"maximum":653928.0,"total":3336947.0,"count":7200,"properties":[]},{"timestamp":"2019-10-02T13:00:00Z","average":334.12902777777776,"minimum":0.0,"maximum":937984.0,"total":2405729.0,"count":7200,"properties":[]},{"timestamp":"2019-10-02T14:00:00Z","average":96.769027777777779,"minimum":0.0,"maximum":20232.0,"total":696737.0,"count":7200,"properties":[]},{"timestamp":"2019-10-02T15:00:00Z","average":96.538194444444443,"minimum":0.0,"maximum":22807.0,"total":695075.0,"count":7200,"properties":[]},{"timestamp":"2019-10-02T16:00:00Z","average":93.27513888888889,"minimum":0.0,"maximum":16919.0,"total":671581.0,"count":7200,"properties":[]},{"timestamp":"2019-10-02T17:00:00Z","average":94.609444444444449,"minimum":0.0,"maximum":22469.0,"total":681188.0,"count":7200,"properties":[]},{"timestamp":"2019-10-02T18:00:00Z","average":98.729166666666671,"minimum":0.0,"maximum":22253.0,"total":710850.0,"count":7200,"properties":[]},{"timestamp":"2019-10-02T19:00:00Z","average":102.67166666666667,"minimum":0.0,"maximum":25427.0,"total":739236.0,"count":7200,"properties":[]},{"timestamp":"2019-10-02T20:00:00Z","average":96.720694444444447,"minimum":0.0,"maximum":22415.0,"total":696389.0,"count":7200,"properties":[]},{"timestamp":"2019-10-02T21:00:00Z","average":93.554583333333326,"minimum":0.0,"maximum":20679.0,"total":673593.0,"count":7200,"properties":[]},{"timestamp":"2019-10-02T22:00:00Z","average":97.839722222222221,"minimum":0.0,"maximum":21118.0,"total":704446.0,"count":7200,"properties":[]},{"timestamp":"2019-10-02T23:00:00Z","average":94.845,"minimum":0.0,"maximum":16743.0,"total":682884.0,"count":7200,"properties":[]},{"timestamp":"2019-10-03T00:00:00Z","average":96.70375,"minimum":0.0,"maximum":21770.0,"total":696267.0,"count":7200,"properties":[]},{"timestamp":"2019-10-03T01:00:00Z","average":93.253055555555562,"minimum":0.0,"maximum":17135.0,"total":671422.0,"count":7200,"properties":[]},{"timestamp":"2019-10-03T02:00:00Z","average":99.270277777777778,"minimum":0.0,"maximum":20903.0,"total":714746.0,"count":7200,"properties":[]},{"timestamp":"2019-10-03T03:00:00Z","average":93.751388888888883,"minimum":0.0,"maximum":22447.0,"total":675010.0,"count":7200,"properties":[]},{"timestamp":"2019-10-03T04:00:00Z","average":98.827361111111117,"minimum":0.0,"maximum":22489.0,"total":711557.0,"count":7200,"properties":[]},{"timestamp":"2019-10-03T05:00:00Z","average":93.538333333333327,"minimum":0.0,"maximum":22387.0,"total":673476.0,"count":7200,"properties":[]},{"timestamp":"2019-10-03T06:00:00Z","average":89.43375,"minimum":0.0,"maximum":25525.0,"total":643923.0,"count":7200,"properties":[]},{"timestamp":"2019-10-03T07:00:00Z","average":96.910972222222227,"minimum":0.0,"maximum":22827.0,"total":697759.0,"count":7200,"properties":[]},{"timestamp":"2019-10-03T08:00:00Z","average":96.767083333333332,"minimum":0.0,"maximum":21118.0,"total":696723.0,"count":7200,"properties":[]},{"timestamp":"2019-10-03T09:00:00Z","average":100.00861111111111,"minimum":0.0,"maximum":23990.0,"total":720062.0,"count":7200,"properties":[]},{"timestamp":"2019-10-03T10:00:00Z","average":93.469861111111115,"minimum":0.0,"maximum":20679.0,"total":672983.0,"count":7200,"properties":[]},{"timestamp":"2019-10-03T11:00:00Z","average":100.16694444444444,"minimum":0.0,"maximum":25149.0,"total":721202.0,"count":7200,"properties":[]},{"timestamp":"2019-10-03T12:00:00Z","average":139.44833333333332,"minimum":0.0,"maximum":301206.0,"total":1004027.9999999999,"count":7200,"properties":[]},{"timestamp":"2019-10-03T13:00:00Z","average":92.662777777777777,"minimum":0.0,"maximum":27281.0,"total":667172.0,"count":7200,"properties":[]},{"timestamp":"2019-10-03T14:00:00Z","average":102.20375,"minimum":0.0,"maximum":21460.0,"total":735867.0,"count":7200,"properties":[]},{"timestamp":"2019-10-03T15:00:00Z","average":96.1751388888889,"minimum":0.0,"maximum":22623.0,"total":692461.0,"count":7200,"properties":[]},{"timestamp":"2019-10-03T16:00:00Z","average":95.251111111111115,"minimum":0.0,"maximum":24774.0,"total":685808.0,"count":7200,"properties":[]},{"timestamp":"2019-10-03T17:00:00Z","average":99.61611111111111,"minimum":0.0,"maximum":22691.0,"total":717236.0,"count":7200,"properties":[]},{"timestamp":"2019-10-03T18:00:00Z","average":98.126111111111115,"minimum":0.0,"maximum":20854.0,"total":706508.0,"count":7200,"properties":[]},{"timestamp":"2019-10-03T19:00:00Z","average":102.62583333333333,"minimum":0.0,"maximum":25961.0,"total":738906.0,"count":7200,"properties":[]},{"timestamp":"2019-10-03T20:00:00Z","average":98.782040229885055,"minimum":0.0,"maximum":82155.0,"total":687523.0,"count":6960,"properties":[]},{"timestamp":"2019-10-03T21:00:00Z","average":159.18193277310925,"minimum":0.0,"maximum":286179.0,"total":1136559.0,"count":7140,"properties":[]},{"timestamp":"2019-10-03T22:00:00Z","average":184.15708333333333,"minimum":0.0,"maximum":55257.0,"total":1325931.0,"count":7200,"properties":[]},{"timestamp":"2019-10-03T23:00:00Z","average":96.760416666666671,"minimum":0.0,"maximum":20679.0,"total":696675.0,"count":7200,"properties":[]},{"timestamp":"2019-10-04T00:00:00Z","average":91.096666666666664,"minimum":0.0,"maximum":16797.0,"total":655896.0,"count":7200,"properties":[]},{"timestamp":"2019-10-04T01:00:00Z","average":93.753472222222229,"minimum":0.0,"maximum":22391.0,"total":675025.0,"count":7200,"properties":[]},{"timestamp":"2019-10-04T02:00:00Z","average":93.290694444444441,"minimum":0.0,"maximum":20679.0,"total":671693.0,"count":7200,"properties":[]},{"timestamp":"2019-10-04T03:00:00Z","average":106.605,"minimum":0.0,"maximum":29093.0,"total":767556.0,"count":7200,"properties":[]},{"timestamp":"2019-10-04T04:00:00Z","average":98.334583333333327,"minimum":0.0,"maximum":22423.0,"total":708009.0,"count":7200,"properties":[]},{"timestamp":"2019-10-04T05:00:00Z","average":98.321111111111108,"minimum":0.0,"maximum":22381.0,"total":707912.0,"count":7200,"properties":[]},{"timestamp":"2019-10-04T06:00:00Z","average":94.364305555555561,"minimum":0.0,"maximum":22295.0,"total":679423.0,"count":7200,"properties":[]},{"timestamp":"2019-10-04T07:00:00Z","average":95.563611111111115,"minimum":0.0,"maximum":20679.0,"total":688058.0,"count":7200,"properties":[]},{"timestamp":"2019-10-04T08:00:00Z","average":88.653194444444438,"minimum":0.0,"maximum":16785.0,"total":638303.0,"count":7200,"properties":[]},{"timestamp":"2019-10-04T09:00:00Z","average":97.167638888888888,"minimum":0.0,"maximum":25091.0,"total":699607.0,"count":7200,"properties":[]},{"timestamp":"2019-10-04T10:00:00Z","average":98.9113888888889,"minimum":0.0,"maximum":19950.0,"total":712162.0,"count":7200,"properties":[]},{"timestamp":"2019-10-04T11:00:00Z","average":95.8775,"minimum":0.0,"maximum":23045.0,"total":690318.0,"count":7200,"properties":[]},{"timestamp":"2019-10-04T12:00:00Z","average":91.415972222222223,"minimum":0.0,"maximum":17075.0,"total":658195.0,"count":7200,"properties":[]},{"timestamp":"2019-10-04T13:00:00Z","average":99.472916666666663,"minimum":0.0,"maximum":22719.0,"total":716205.0,"count":7200,"properties":[]},{"timestamp":"2019-10-04T14:00:00Z","average":93.183888888888887,"minimum":0.0,"maximum":16731.0,"total":670924.0,"count":7200,"properties":[]},{"timestamp":"2019-10-04T15:00:00Z","average":98.712777777777774,"minimum":0.0,"maximum":22253.0,"total":710732.0,"count":7200,"properties":[]},{"timestamp":"2019-10-04T16:00:00Z","average":102.08930555555555,"minimum":0.0,"maximum":31503.0,"total":735043.0,"count":7200,"properties":[]},{"timestamp":"2019-10-04T17:00:00Z","average":94.955694444444447,"minimum":0.0,"maximum":22327.0,"total":683681.0,"count":7200,"properties":[]},{"timestamp":"2019-10-04T18:00:00Z","average":94.638888888888886,"minimum":0.0,"maximum":19841.0,"total":681400.0,"count":7200,"properties":[]},{"timestamp":"2019-10-04T19:00:00Z","average":390.80791666666664,"minimum":0.0,"maximum":847593.0,"total":2813817.0,"count":7200,"properties":[]},{"timestamp":"2019-10-04T20:00:00Z","average":108.68027777777777,"minimum":0.0,"maximum":16797.0,"total":782498.0,"count":7200,"properties":[]},{"timestamp":"2019-10-04T21:00:00Z","average":596.88944444444439,"minimum":0.0,"maximum":892690.0,"total":4297604.0,"count":7200,"properties":[]},{"timestamp":"2019-10-04T22:00:00Z","average":131.68111111111111,"minimum":0.0,"maximum":178098.0,"total":948104.0,"count":7200,"properties":[]},{"timestamp":"2019-10-04T23:00:00Z","average":96.435416666666669,"minimum":0.0,"maximum":21658.0,"total":694335.0,"count":7200,"properties":[]},{"timestamp":"2019-10-05T00:00:00Z","average":97.170416666666668,"minimum":0.0,"maximum":26397.0,"total":699627.0,"count":7200,"properties":[]},{"timestamp":"2019-10-05T01:00:00Z","average":94.586388888888891,"minimum":0.0,"maximum":25373.0,"total":681022.0,"count":7200,"properties":[]},{"timestamp":"2019-10-05T02:00:00Z","average":93.465,"minimum":0.0,"maximum":21077.0,"total":672948.0,"count":7200,"properties":[]},{"timestamp":"2019-10-05T03:00:00Z","average":99.89875,"minimum":0.0,"maximum":25821.0,"total":719271.0,"count":7200,"properties":[]},{"timestamp":"2019-10-05T04:00:00Z","average":95.012638888888887,"minimum":0.0,"maximum":19055.0,"total":684091.0,"count":7200,"properties":[]},{"timestamp":"2019-10-05T05:00:00Z","average":95.638055555555553,"minimum":0.0,"maximum":17189.0,"total":688594.0,"count":7200,"properties":[]},{"timestamp":"2019-10-05T06:00:00Z","average":99.166388888888889,"minimum":0.0,"maximum":22369.0,"total":713998.0,"count":7200,"properties":[]},{"timestamp":"2019-10-05T07:00:00Z","average":93.230138888888888,"minimum":0.0,"maximum":22295.0,"total":671257.0,"count":7200,"properties":[]},{"timestamp":"2019-10-05T08:00:00Z","average":93.235833333333332,"minimum":0.0,"maximum":21138.0,"total":671298.0,"count":7200,"properties":[]},{"timestamp":"2019-10-05T09:00:00Z","average":96.84708333333333,"minimum":0.0,"maximum":22575.0,"total":697299.0,"count":7200,"properties":[]},{"timestamp":"2019-10-05T10:00:00Z","average":95.600277777777777,"minimum":0.0,"maximum":21588.0,"total":688322.0,"count":7200,"properties":[]},{"timestamp":"2019-10-05T11:00:00Z","average":96.564722222222215,"minimum":0.0,"maximum":22295.0,"total":695266.0,"count":7200,"properties":[]},{"timestamp":"2019-10-05T12:00:00Z","average":97.063194444444449,"minimum":0.0,"maximum":22645.0,"total":698855.0,"count":7200,"properties":[]},{"timestamp":"2019-10-05T13:00:00Z","average":96.464444444444439,"minimum":0.0,"maximum":21738.0,"total":694544.0,"count":7200,"properties":[]},{"timestamp":"2019-10-05T14:00:00Z","average":92.7925,"minimum":0.0,"maximum":22175.0,"total":668106.0,"count":7200,"properties":[]},{"timestamp":"2019-10-05T15:00:00Z","average":98.336666666666673,"minimum":0.0,"maximum":22965.0,"total":708024.0,"count":7200,"properties":[]},{"timestamp":"2019-10-05T16:00:00Z","average":97.888611111111118,"minimum":0.0,"maximum":22661.0,"total":704798.0,"count":7200,"properties":[]},{"timestamp":"2019-10-05T17:00:00Z","average":95.439027777777781,"minimum":0.0,"maximum":22423.0,"total":687161.0,"count":7200,"properties":[]},{"timestamp":"2019-10-05T18:00:00Z","average":96.095694444444447,"minimum":0.0,"maximum":22551.0,"total":691889.0,"count":7200,"properties":[]},{"timestamp":"2019-10-05T19:00:00Z","average":96.563472222222217,"minimum":0.0,"maximum":23189.0,"total":695257.0,"count":7200,"properties":[]},{"timestamp":"2019-10-05T20:00:00Z","average":96.855833333333337,"minimum":0.0,"maximum":22477.0,"total":697362.0,"count":7200,"properties":[]},{"timestamp":"2019-10-05T21:00:00Z","average":99.685833333333335,"minimum":0.0,"maximum":27352.0,"total":717738.0,"count":7200,"properties":[]},{"timestamp":"2019-10-05T22:00:00Z","average":97.586666666666673,"minimum":0.0,"maximum":22639.0,"total":702624.0,"count":7200,"properties":[]},{"timestamp":"2019-10-05T23:00:00Z","average":181.52666666666667,"minimum":0.0,"maximum":42816.0,"total":1306992.0,"count":7200,"properties":[]},{"timestamp":"2019-10-06T00:00:00Z","average":106.63194444444444,"minimum":0.0,"maximum":69881.0,"total":767750.0,"count":7200,"properties":[]},{"timestamp":"2019-10-06T01:00:00Z","average":96.00277777777778,"minimum":0.0,"maximum":21143.0,"total":691220.0,"count":7200,"properties":[]},{"timestamp":"2019-10-06T02:00:00Z","average":99.48875,"minimum":0.0,"maximum":22673.0,"total":716319.0,"count":7200,"properties":[]},{"timestamp":"2019-10-06T03:00:00Z","average":99.201805555555552,"minimum":0.0,"maximum":22381.0,"total":714253.0,"count":7200,"properties":[]},{"timestamp":"2019-10-06T04:00:00Z","average":97.201388888888886,"minimum":0.0,"maximum":21880.0,"total":699850.0,"count":7200,"properties":[]},{"timestamp":"2019-10-06T05:00:00Z","average":96.241944444444442,"minimum":0.0,"maximum":20749.0,"total":692942.0,"count":7200,"properties":[]},{"timestamp":"2019-10-06T06:00:00Z","average":97.888611111111118,"minimum":0.0,"maximum":22423.0,"total":704798.0,"count":7200,"properties":[]},{"timestamp":"2019-10-06T07:00:00Z","average":97.514305555555552,"minimum":0.0,"maximum":22777.0,"total":702103.0,"count":7200,"properties":[]},{"timestamp":"2019-10-06T08:00:00Z","average":92.670277777777784,"minimum":0.0,"maximum":20749.0,"total":667226.0,"count":7200,"properties":[]},{"timestamp":"2019-10-06T09:00:00Z","average":96.467083333333335,"minimum":0.0,"maximum":22489.0,"total":694563.0,"count":7200,"properties":[]},{"timestamp":"2019-10-06T10:00:00Z","average":93.620138888888889,"minimum":0.0,"maximum":20691.0,"total":674065.0,"count":7200,"properties":[]},{"timestamp":"2019-10-06T11:00:00Z","average":136.64013888888888,"minimum":0.0,"maximum":22799.0,"total":983809.0,"count":7200,"properties":[]},{"timestamp":"2019-10-06T12:00:00Z","average":148.32027777777779,"minimum":0.0,"maximum":34635.0,"total":1067906.0,"count":7200,"properties":[]},{"timestamp":"2019-10-06T13:00:00Z","average":93.609166666666667,"minimum":0.0,"maximum":17135.0,"total":673986.0,"count":7200,"properties":[]},{"timestamp":"2019-10-06T14:00:00Z","average":91.296111111111117,"minimum":0.0,"maximum":17701.0,"total":657332.0,"count":7200,"properties":[]},{"timestamp":"2019-10-06T15:00:00Z","average":104.61694444444444,"minimum":0.0,"maximum":22349.0,"total":753242.0,"count":7200,"properties":[]},{"timestamp":"2019-10-06T16:00:00Z","average":354.77138888888891,"minimum":0.0,"maximum":138775.0,"total":2554354.0,"count":7200,"properties":[]},{"timestamp":"2019-10-06T17:00:00Z","average":98.856388888888887,"minimum":0.0,"maximum":26063.0,"total":711766.0,"count":7200,"properties":[]},{"timestamp":"2019-10-06T18:00:00Z","average":94.893611111111113,"minimum":0.0,"maximum":25633.0,"total":683234.0,"count":7200,"properties":[]},{"timestamp":"2019-10-06T19:00:00Z","average":90.066527777777779,"minimum":0.0,"maximum":17883.0,"total":648479.0,"count":7200,"properties":[]},{"timestamp":"2019-10-06T20:00:00Z","average":97.59319444444445,"minimum":0.0,"maximum":25392.0,"total":702671.0,"count":7200,"properties":[]},{"timestamp":"2019-10-06T21:00:00Z","average":102.815,"minimum":0.0,"maximum":25949.0,"total":740268.0,"count":7200,"properties":[]},{"timestamp":"2019-10-06T22:00:00Z","average":96.326666666666668,"minimum":0.0,"maximum":25150.0,"total":693552.0,"count":7200,"properties":[]},{"timestamp":"2019-10-06T23:00:00Z","average":96.923194444444448,"minimum":0.0,"maximum":22659.0,"total":697847.0,"count":7200,"properties":[]},{"timestamp":"2019-10-07T00:00:00Z","average":102.1751388888889,"minimum":0.0,"maximum":22999.0,"total":735661.0,"count":7200,"properties":[]},{"timestamp":"2019-10-07T01:00:00Z","average":97.212222222222223,"minimum":0.0,"maximum":22489.0,"total":699928.0,"count":7200,"properties":[]},{"timestamp":"2019-10-07T02:00:00Z","average":96.305277777777775,"minimum":0.0,"maximum":20679.0,"total":693398.0,"count":7200,"properties":[]},{"timestamp":"2019-10-07T03:00:00Z","average":97.839444444444439,"minimum":0.0,"maximum":17147.0,"total":704444.0,"count":7200,"properties":[]},{"timestamp":"2019-10-07T04:00:00Z","average":95.3626388888889,"minimum":0.0,"maximum":22661.0,"total":686611.0,"count":7200,"properties":[]},{"timestamp":"2019-10-07T05:00:00Z","average":102.79708333333333,"minimum":0.0,"maximum":25445.0,"total":740139.0,"count":7200,"properties":[]},{"timestamp":"2019-10-07T06:00:00Z","average":95.172916666666666,"minimum":0.0,"maximum":16893.0,"total":685245.0,"count":7200,"properties":[]},{"timestamp":"2019-10-07T07:00:00Z","average":99.739583333333329,"minimum":0.0,"maximum":22843.0,"total":718125.0,"count":7200,"properties":[]},{"timestamp":"2019-10-07T08:00:00Z","average":98.8875,"minimum":0.0,"maximum":25149.0,"total":711990.0,"count":7200,"properties":[]},{"timestamp":"2019-10-07T09:00:00Z","average":97.19638888888889,"minimum":0.0,"maximum":23221.0,"total":699814.0,"count":7200,"properties":[]},{"timestamp":"2019-10-07T10:00:00Z","average":99.678472222222226,"minimum":0.0,"maximum":22423.0,"total":717685.0,"count":7200,"properties":[]},{"timestamp":"2019-10-07T11:00:00Z","average":90.7213888888889,"minimum":0.0,"maximum":16743.0,"total":653194.0,"count":7200,"properties":[]},{"timestamp":"2019-10-07T12:00:00Z","average":93.532916666666665,"minimum":0.0,"maximum":25589.0,"total":673437.0,"count":7200,"properties":[]},{"timestamp":"2019-10-07T13:00:00Z","average":94.043194444444438,"minimum":0.0,"maximum":21448.0,"total":677111.0,"count":7200,"properties":[]},{"timestamp":"2019-10-07T14:00:00Z","average":91.260138888888889,"minimum":0.0,"maximum":17075.0,"total":657073.0,"count":7200,"properties":[]},{"timestamp":"2019-10-07T15:00:00Z","average":94.69,"minimum":0.0,"maximum":16839.0,"total":681768.0,"count":7200,"properties":[]},{"timestamp":"2019-10-07T16:00:00Z","average":363.50777777777779,"minimum":0.0,"maximum":723665.0,"total":2617256.0,"count":7200,"properties":[]},{"timestamp":"2019-10-07T17:00:00Z","average":93.488194444444446,"minimum":0.0,"maximum":20745.0,"total":673115.0,"count":7200,"properties":[]},{"timestamp":"2019-10-07T18:00:00Z","average":583.66208333333338,"minimum":0.0,"maximum":671556.0,"total":4202367.0,"count":7200,"properties":[]},{"timestamp":"2019-10-07T19:00:00Z","average":143.71291666666667,"minimum":0.0,"maximum":182468.0,"total":1034733.0,"count":7200,"properties":[]},{"timestamp":"2019-10-07T20:00:00Z","average":97.258611111111108,"minimum":0.0,"maximum":16973.0,"total":700262.0,"count":7200,"properties":[]},{"timestamp":"2019-10-07T21:00:00Z","average":98.259444444444441,"minimum":0.0,"maximum":20640.0,"total":707468.0,"count":7200,"properties":[]},{"timestamp":"2019-10-07T22:00:00Z","average":98.9336111111111,"minimum":0.0,"maximum":21836.0,"total":712322.0,"count":7200,"properties":[]},{"timestamp":"2019-10-07T23:00:00Z","average":95.975,"minimum":0.0,"maximum":22773.0,"total":691020.0,"count":7200,"properties":[]},{"timestamp":"2019-10-08T00:00:00Z","average":93.671805555555551,"minimum":0.0,"maximum":22489.0,"total":674437.0,"count":7200,"properties":[]},{"timestamp":"2019-10-08T01:00:00Z","average":94.5525,"minimum":0.0,"maximum":20800.0,"total":680778.0,"count":7200,"properties":[]},{"timestamp":"2019-10-08T02:00:00Z","average":94.305972222222223,"minimum":0.0,"maximum":16743.0,"total":679003.0,"count":7200,"properties":[]},{"timestamp":"2019-10-08T03:00:00Z","average":98.85375,"minimum":0.0,"maximum":22551.0,"total":711747.0,"count":7200,"properties":[]},{"timestamp":"2019-10-08T04:00:00Z","average":103.66444444444444,"minimum":0.0,"maximum":20800.0,"total":746384.0,"count":7200,"properties":[]},{"timestamp":"2019-10-08T05:00:00Z","average":93.712083333333339,"minimum":0.0,"maximum":25821.0,"total":674727.0,"count":7200,"properties":[]},{"timestamp":"2019-10-08T06:00:00Z","average":95.240972222222226,"minimum":0.0,"maximum":22371.0,"total":685735.0,"count":7200,"properties":[]},{"timestamp":"2019-10-08T07:00:00Z","average":139.425,"minimum":0.0,"maximum":16731.0,"total":16731.0,"count":120,"properties":[]}],"resourceId":null,"properties":[],"id":"/subscriptions/bbd83110-10a9-4d2f-9b08-ec69f129c56b/resourceGroups/webflowersproductcentral/providers/Microsoft.ClassicCompute/domainNames/webflowersproductcentral/slots/Production/roles/GloboStudio.Core.WebServices/metrics/Network Out"}]}